exc_to_pdf/__init__.py
exc_to_pdf/bookmark_manager.py
exc_to_pdf/cache_manager.py
exc_to_pdf/data_validator.py
exc_to_pdf/excel_processor.py
exc_to_pdf/exceptions.py
exc_to_pdf/main.py
exc_to_pdf/memory_monitor.py
exc_to_pdf/metadata_manager.py
exc_to_pdf/pdf_generator.py
exc_to_pdf/pdf_table_renderer.py
exc_to_pdf/progress_tracker.py
exc_to_pdf/streaming_excel_processor.py
exc_to_pdf/table_detector.py
exc_to_pdf/chart/__init__.py
exc_to_pdf/chart/chart_extractor.py
exc_to_pdf/chart/chart_recreator.py
exc_to_pdf/chart/chart_renderer.py
exc_to_pdf/config/__init__.py
exc_to_pdf/config/excel_config.py
exc_to_pdf/config/pdf_config.py
exc_to_pdf/i18n/__init__.py
exc_to_pdf/i18n/formatters.py
exc_to_pdf/i18n/locale_manager.py
exc_to_pdf/templates/__init__.py
exc_to_pdf/templates/style_presets.py
exc_to_pdf/templates/template_config.py
exc_to_pdf/templates/template_manager.py
exc_to_pdf-1.0.0.dist-info/licenses/LICENSE
exc_to_pdf-1.0.0.dist-info/METADATA
exc_to_pdf-1.0.0.dist-info/WHEEL
exc_to_pdf-1.0.0.dist-info/entry_points.txt
exc_to_pdf-1.0.0.dist-info/top_level.txt
exc_to_pdf-1.0.0.dist-info/RECORD
