Metadata-Version: 2.4
Name: exc-to-pdf
Version: 1.0.0
Summary: Excel to PDF converter optimized for Google NotebookLM
Author-email: exc-to-pdf team <contact@example.com>
License-Expression: MIT
Project-URL: Homepage, https://github.com/fulvian/exc-to-pdf
Project-URL: Documentation, https://fulvian.github.io/exc-to-pdf
Project-URL: Repository, https://github.com/fulvian/exc-to-pdf
Project-URL: Bug Tracker, https://github.com/fulvian/exc-to-pdf/issues
Project-URL: Changelog, https://github.com/fulvian/exc-to-pdf/blob/main/CHANGELOG.md
Keywords: excel,pdf,converter,notebooklm,ai
Classifier: Development Status :: 5 - Production/Stable
Classifier: Intended Audience :: Developers
Classifier: Intended Audience :: End Users/Desktop
Classifier: Operating System :: OS Independent
Classifier: Programming Language :: Python :: 3
Classifier: Programming Language :: Python :: 3.9
Classifier: Programming Language :: Python :: 3.10
Classifier: Programming Language :: Python :: 3.11
Classifier: Programming Language :: Python :: 3.12
Classifier: Topic :: Office/Business
Classifier: Topic :: Multimedia :: Graphics
Classifier: Topic :: Software Development :: Libraries :: Python Modules
Classifier: Topic :: Text Processing
Requires-Python: >=3.9
License-File: LICENSE
Requires-Dist: openpyxl>=3.1.0
Requires-Dist: pandas>=2.0.0
Requires-Dist: reportlab>=4.0.0
Requires-Dist: Pillow>=10.0.0
Requires-Dist: matplotlib>=3.7.0
Requires-Dist: babel>=2.12.0
Requires-Dist: pytz>=2023.3
Requires-Dist: numpy>=1.24.0
Requires-Dist: structlog>=23.0.0
Requires-Dist: click>=8.0.0
Requires-Dist: psutil>=5.9.0
Provides-Extra: dev
Requires-Dist: pytest>=7.0.0; extra == "dev"
Requires-Dist: pytest-cov>=4.0.0; extra == "dev"
Requires-Dist: black>=23.0.0; extra == "dev"
Requires-Dist: flake8>=6.0.0; extra == "dev"
Requires-Dist: mypy>=1.0.0; extra == "dev"
Provides-Extra: test
Requires-Dist: pytest>=7.0.0; extra == "test"
Requires-Dist: pytest-cov>=4.0.0; extra == "test"
Requires-Dist: mypy>=1.0.0; extra == "test"
Dynamic: license-file
